django_immortalmodel-1.0.0.dist-info/METADATA
django_immortalmodel-1.0.0.dist-info/RECORD
django_immortalmodel-1.0.0.dist-info/WHEEL
django_immortalmodel-1.0.0.dist-info/top_level.txt
immortalmodel/__init__.py
immortalmodel/admin.py
immortalmodel/models.py
immortalmodel/tests.py
